LICENSE
MANIFEST.in
README.md
setup.py
dependency_paraphraser/__init__.py
dependency_paraphraser/natasha.py
dependency_paraphraser/pretrained_projectors.py
dependency_paraphraser/projection.py
dependency_paraphraser/synonyms.py
dependency_paraphraser/train_projector.py
dependency_paraphraser/udpipe.py
dependency_paraphraser/utils.py
dependency_paraphraser.egg-info/PKG-INFO
dependency_paraphraser.egg-info/SOURCES.txt
dependency_paraphraser.egg-info/dependency_links.txt
dependency_paraphraser.egg-info/requires.txt
dependency_paraphraser.egg-info/top_level.txt
dependency_paraphraser/models/en_udpipe_projector.pkl
dependency_paraphraser/models/natasha_projector.pkl