Metadata-Version: 2.1
Name: dependency-paraphraser
Version: 0.0.5
Summary: A sentence paraphraser based on dependency syntax and word embeddings
Home-page: https://github.com/avidale/dependency-paraphraser
Author: David Dale
Author-email: dale.david@mail.ru
License: MIT
Platform: UNKNOWN
Classifier: Development Status :: 3 - Alpha
Classifier: Programming Language :: Python :: 3
Classifier: License :: OSI Approved :: MIT License
Classifier: Operating System :: OS Independent
Provides-Extra: natasha
Provides-Extra: udpipe
